Marker.py
RigidBody.py
__init__.py
PyRigidBody-0.0.1.dist-info/LICENSE
PyRigidBody-0.0.1.dist-info/METADATA
PyRigidBody-0.0.1.dist-info/WHEEL
PyRigidBody-0.0.1.dist-info/top_level.txt
PyRigidBody-0.0.1.dist-info/RECORD
