Metadata-Version: 2.1
Name: PyRigidBody
Version: 0.0.1
Summary: A package for handling rigid body transformations and markers in 3D space
Author-email: Berat Atmaca <beratatmaca@live.com>
Project-URL: Homepage, https://github.com/beratatmaca/PyRigidBody
Project-URL: Issues, https://github.com/beratatmaca/PyRigidBody/issues
Classifier: Programming Language :: Python :: 3
Classifier: License :: OSI Approved :: MIT License
Classifier: Operating System :: OS Independent
Requires-Python: >=3.7
License-File: LICENSE
Provides-Extra: testing
Requires-Dist: pytest ; extra == 'testing'
